ALU.v
module alu(
           input [7:0] A,B,  // ALU 8-bit Inputs                 
           input [3:0] ALU_Sel,// ALU Selection
           output [7:0] ALU_Out, // ALU 8-bit Output
           output CarryOut // Carry Out Flag
    );
    reg [7:0] ALU_Result;
    wire [8:0] tmp;
    assign ALU_Out = ALU_Result; // ALU out
    assign tmp = {1'b0,A} + {1'b0,B};
    assign CarryOut = tmp[8]; // Carryout flag
    always @(*)
    begin
        case(ALU_Sel)
        4'b0000: // Addition
           ALU_Result = A + B ; 
        4'b0001: // Subtraction
           ALU_Result = A - B ;
        4'b0010: // Logical shift left
           ALU_Result = A<<1;
        4'b0011: // Logical shift right
           ALU_Result = A>>1;
        4'b0100: // Rotate left
           ALU_Result = {A[6:0],A[7]};
        4'b0101: // Rotate right
           ALU_Result = {A[0],A[7:1]};
        4'b0110: //  Logical and 
           ALU_Result = A & B;
        4'b0111: //  Logical or
           ALU_Result = A | B;
        4'b1000: //  Logical xor 
           ALU_Result = A ^ B;
        4'b1001: // Greater comparison
           ALU_Result = (A>B)?8'd1:8'd0 ;
        4'b1010: // Equal comparison   
            ALU_Result = (A==B)?8'd1:8'd0 ;
        default: ALU_Result = A + B ; 
        endcase
    end

endmodule

sim/tb.v
`timescale 1ns / 1ps  

module tb_alu;
//Inputs
 reg[7:0] A,B;
 reg[3:0] ALU_Sel;

//Outputs
 wire[7:0] ALU_Out;
 wire CarryOut;
 // Verilog code for ALU
 integer i;
 alu dut( .A(A),.B(B),  // ALU 8-bit Inputs                 
          .ALU_Sel(ALU_Sel),// ALU Selection
          .ALU_Out(ALU_Out), // ALU 8-bit Output
          .CarryOut(CarryOut) // Carry Out Flag
     );
    initial begin
    
      $dumpfile("dump.vcd");
      $dumpvars(0, tb_alu);
      
      // hold reset state for 100 ns.
      A = 8'h0A;
      B = 8'h02;
      ALU_Sel = 4'h0;
      
      for (i=0;i<=11;i=i+1)
      begin
       #10;
       ALU_Sel = ALU_Sel + 8'h01;
      end;
      
      A = 8'hF6;
      B = 8'h0A;
      
    end
endmodule

sim/dump.vcd
$date
	Fri Feb 09 10:21:15 2024
$end
$version
	Icarus Verilog
$end
$timescale
	1ps
$end
$scope module tb_alu $end
$var wire 1 ! CarryOut $end
$var wire 8 " ALU_Out [7:0] $end
$var reg 8 # A [7:0] $end
$var reg 4 $ ALU_Sel [3:0] $end
$var reg 8 % B [7:0] $end
$var integer 32 & i [31:0] $end
$scope module dut $end
$var wire 8 ' A [7:0] $end
$var wire 8 ( ALU_Out [7:0] $end
$var wire 4 ) ALU_Sel [3:0] $end
$var wire 8 * B [7:0] $end
$var wire 9 + tmp [8:0] $end
$var wire 1 ! CarryOut $end
$var reg 8 , ALU_Result [7:0] $end
$upscope $end
$upscope $end
$enddefinitions $end
$comment Show the parameter values. $end
$dumpall
$end
#0
$dumpvars
b1100 ,
b1100 +
b10 *
b0 )
b1100 (
b1010 '
b0 &
b10 %
b0 $
b1010 #
b1100 "
0!
$end
#10000
b1000 "
b1000 (
b1000 ,
b1 &
b1 $
b1 )
#20000
b10100 "
b10100 (
b10100 ,
b10 &
b10 $
b10 )
#30000
b101 "
b101 (
b101 ,
b11 &
b11 $
b11 )
#40000
b10100 "
b10100 (
b10100 ,
b100 &
b100 $
b100 )
#50000
b101 "
b101 (
b101 ,
b101 &
b101 $
b101 )
#60000
b10 "
b10 (
b10 ,
b110 &
b110 $
b110 )
#70000
b1010 "
b1010 (
b1010 ,
b111 &
b111 $
b111 )
#80000
b1000 "
b1000 (
b1000 ,
b1000 &
b1000 $
b1000 )
#90000
b1 "
b1 (
b1 ,
b1001 &
b1001 $
b1001 )
#100000
b0 "
b0 (
b0 ,
b1010 &
b1010 $
b1010 )
#110000
b1100 "
b1100 (
b1100 ,
b1011 &
b1011 $
b1011 )
#120000
1!
b0 "
b0 (
b0 ,
b1010 %
b1010 *
b100000000 +
b11110110 #
b11110110 '
b1100 &
b1100 $
b1100 )
